{
  "job_id": "0e310fc0168043389708d7529f1f8088",
  "tempo_bpm": 69.83741554054055,
  "time_signature": "4/4",
  "key_signature": {
    "tonic": "G",
    "mode": "major",
    "fifths": 1,
    "name": "G major",
    "vexflow": "G",
    "use_flats": false,
    "score": 0.961759626865387
  },
  "chords": [
    {
      "start": 0.0,
      "end": 0.3947392161935568,
      "label": "N",
      "confidence": 0.09887350350618362
    },
    {
      "start": 0.3947392404079437,
      "end": 0.8823582585901022,
      "label": "G:maj7",
      "confidence": 0.027656646445393562
    },
    {
      "start": 0.8823582530021667,
      "end": 3.134693806990981,
      "label": "N",
      "confidence": 0.03711013123393059
    },
    {
      "start": 3.1346938610076904,
      "end": 4.005442088469863,
      "label": "D:maj",
      "confidence": 0.029081739485263824
    },
    {
      "start": 4.005442142486572,
      "end": 7.302675670012832,
      "label": "A:min7",
      "confidence": 0.026092441752552986
    },
    {
      "start": 7.302675724029541,
      "end": 9.311201995238662,
      "label": "G:maj7",
      "confidence": 0.025551550090312958
    },
    {
      "start": 9.311202049255371,
      "end": 11.017868941649795,
      "label": "D:maj7",
      "confidence": 0.026839496567845345
    },
    {
      "start": 11.017868041992188,
      "end": 12.829025214537978,
      "label": "C:maj7",
      "confidence": 0.027422944083809853
    },
    {
      "start": 12.829025268554688,
      "end": 13.246984427794814,
      "label": "N",
      "confidence": 0.028833160176873207
    },
    {
      "start": 13.246984481811523,
      "end": 13.68816370330751,
      "label": "C:maj7",
      "confidence": 0.027903007343411446
    },
    {
      "start": 13.688162803649902,
      "end": 14.117731994017959,
      "label": "N",
      "confidence": 0.02153569646179676
    },
    {
      "start": 14.117732048034668,
      "end": 15.313560431823134,
      "label": "G:maj7",
      "confidence": 0.025067340582609177
    }
  ],
  "transcription_backend": "basic_pitch+chords_viterbi",
  "transcription_error": null,
  "score": {
    "grid_q": 0.25,
    "grid_kind": "straight",
    "measures": [
      {
        "number": 1,
        "items": [
          {
            "rest": false,
            "keys": [
              "g/2",
              "d/3"
            ],
            "duration": "h",
            "dots": 0,
            "tuplet": null,
            "tie": null
          },
          {
            "rest": false,
            "keys": [
              "g/2",
              "d/3",
              "g/3"
            ],
            "duration": "q",
            "dots": 0,
            "tuplet": null,
            "tie": null
          },
          {
            "rest": false,
            "keys": [
              "g/2",
              "d/3"
            ],
            "duration": "8",
            "dots": 0,
            "tuplet": null,
            "tie": null
          },
          {
            "rest": false,
            "keys": [
              "g/2"
            ],
            "duration": "16",
            "dots": 0,
            "tuplet": null,
            "tie": null
          },
          {
            "rest": false,
            "keys": [
              "g/2",
              "d/3"
            ],
            "duration": "16",
            "dots": 0,
            "tuplet": null,
            "tie": null
          }
        ]
      },
      {
        "number": 2,
        "items": [
          {
            "rest": false,
            "keys": [
              "g/2",
              "d/3"
            ],
            "duration": "16",
            "dots": 0,
            "tuplet": null,
            "tie": null
          },
          {
            "rest": false,
            "keys": [
              "d/3",
              "f#/4"
            ],
            "duration": "h",
            "dots": 1,
            "tuplet": null,
            "tie": null
          },
          {
            "rest": false,
            "keys": [
              "d/3"
            ],
            "duration": "8",
            "dots": 1,
            "tuplet": null,
            "tie": null
          }
        ]
      },
      {
        "number": 3,
        "items": [
          {
            "rest": false,
            "keys": [
              "a/2"
            ],
            "duration": "16",
            "dots": 0,
            "tuplet": null,
            "tie": null
          },
          {
            "rest": false,
            "keys": [
              "e/2",
              "a/2"
            ],
            "duration": "8",
            "dots": 0,
            "tuplet": null,
            "tie": null
          },
          {
            "rest": false,
            "keys": [
              "e/2",
              "a/2",
              "c/3"
            ],
            "duration": "8",
            "dots": 1,
            "tuplet": null,
            "tie": null
          },
          {
            "rest": false,
            "keys": [
              "e/2",
              "a/2",
              "c/3",
              "e/4"
            ],
            "duration": "16",
            "dots": 0,
            "tuplet": null,
            "tie": null
          },
          {
            "rest": false,
            "keys": [
              "a/2",
              "c/3",
              "e/4"
            ],
            "duration": "16",
            "dots": 0,
            "tuplet": null,
            "tie": null
          },
          {
            "rest": false,
            "keys": [
              "a/2",
              "c/3"
            ],
            "duration": "8",
            "dots": 0,
            "tuplet": null,
            "tie": null
          },
          {
            "rest": false,
            "keys": [
              "a/2",
              "c/3",
              "c/4"
            ],
            "duration": "8",
            "dots": 1,
            "tuplet": null,
            "tie": null
          },
          {
            "rest": false,
            "keys": [
              "a/2",
              "c/3"
            ],
            "duration": "8",
            "dots": 1,
            "tuplet": null,
            "tie": null
          }
        ]
      },
      {
        "number": 4,
        "items": [
          {
            "rest": false,
            "keys": [
              "a/2",
              "c/3"
            ],
            "duration": "8",
            "dots": 0,
            "tuplet": null,
            "tie": null
          },
          {
            "rest": false,
            "keys": [
              "a/2"
            ],
            "duration": "h",
            "dots": 1,
            "tuplet": null,
            "tie": null
          },
          {
            "rest": true,
            "keys": [],
            "duration": "16",
            "dots": 0,
            "tuplet": null,
            "tie": null
          },
          {
            "rest": false,
            "keys": [
              "g/3"
            ],
            "duration": "16",
            "dots": 0,
            "tuplet": null,
            "tie": null
          }
        ]
      },
      {
        "number": 5,
        "items": [
          {
            "rest": false,
            "keys": [
              "g/3"
            ],
            "duration": "q",
            "dots": 0,
            "tuplet": null,
            "tie": "start"
          },
          {
            "rest": false,
            "keys": [
              "g/3"
            ],
            "duration": "16",
            "dots": 0,
            "tuplet": null,
            "tie": "stop"
          },
          {
            "rest": false,
            "keys": [
              "g/3",
              "g/4"
            ],
            "duration": "q",
            "dots": 1,
            "tuplet": null,
            "tie": "start"
          },
          {
            "rest": false,
            "keys": [
              "g/3",
              "g/4"
            ],
            "duration": "16",
            "dots": 0,
            "tuplet": null,
            "tie": "stop"
          },
          {
            "rest": false,
            "keys": [
              "g/4"
            ],
            "duration": "16",
            "dots": 0,
            "tuplet": null,
            "tie": null
          },
          {
            "rest": false,
            "keys": [
              "d/4",
              "g/4"
            ],
            "duration": "16",
            "dots": 0,
            "tuplet": null,
            "tie": null
          },
          {
            "rest": false,
            "keys": [
              "g/2",
              "d/4",
              "g/4"
            ],
            "duration": "8",
            "dots": 0,
            "tuplet": null,
            "tie": null
          }
        ]
      },
      {
        "number": 6,
        "items": [
          {
            "rest": false,
            "keys": [
              "g/2",
              "d/4",
              "g/4"
            ],
            "duration": "16",
            "dots": 0,
            "tuplet": null,
            "tie": null
          },
          {
            "rest": false,
            "keys": [
              "d/3",
              "g/4"
            ],
            "duration": "16",
            "dots": 0,
            "tuplet": null,
            "tie": null
          },
          {
            "rest": false,
            "keys": [
              "d/3"
            ],
            "duration": "16",
            "dots": 0,
            "tuplet": null,
            "tie": null
          },
          {
            "rest": false,
            "keys": [
              "d/3",
              "f#/4"
            ],
            "duration": "8",
            "dots": 0,
            "tuplet": null,
            "tie": null
          },
          {
            "rest": false,
            "keys": [
              "d/3",
              "f#/3",
              "f#/4"
            ],
            "duration": "q",
            "dots": 0,
            "tuplet": null,
            "tie": null
          },
          {
            "rest": false,
            "keys": [
              "d/3",
              "f#/3",
              "d/4",
              "f#/4"
            ],
            "duration": "q",
            "dots": 0,
            "tuplet": null,
            "tie": "start"
          },
          {
            "rest": false,
            "keys": [
              "d/3",
              "f#/3",
              "d/4",
              "f#/4"
            ],
            "duration": "16",
            "dots": 0,
            "tuplet": null,
            "tie": "stop"
          },
          {
            "rest": false,
            "keys": [
              "f#/3",
              "d/4",
              "f#/4"
            ],
            "duration": "8",
            "dots": 0,
            "tuplet": null,
            "tie": null
          }
        ]
      },
      {
        "number": 7,
        "items": [
          {
            "rest": false,
            "keys": [
              "d/3",
              "f#/3",
              "d/4",
              "f#/4"
            ],
            "duration": "16",
            "dots": 0,
            "tuplet": null,
            "tie": null
          },
          {
            "rest": false,
            "keys": [
              "d/3",
              "f#/3",
              "d/4"
            ],
            "duration": "16",
            "dots": 0,
            "tuplet": null,
            "tie": null
          },
          {
            "rest": false,
            "keys": [
              "d/3",
              "f#/3"
            ],
            "duration": "16",
            "dots": 0,
            "tuplet": null,
            "tie": null
          },
          {
            "rest": false,
            "keys": [
              "g/3"
            ],
            "duration": "16",
            "dots": 0,
            "tuplet": null,
            "tie": null
          },
          {
            "rest": false,
            "keys": [
              "c/3",
              "e/3",
              "g/3"
            ],
            "duration": "8",
            "dots": 0,
            "tuplet": null,
            "tie": null
          },
          {
            "rest": false,
            "keys": [
              "c/3",
              "e/3"
            ],
            "duration": "8",
            "dots": 1,
            "tuplet": null,
            "tie": null
          },
          {
            "rest": false,
            "keys": [
              "c/3",
              "e/3",
              "e/4"
            ],
            "duration": "8",
            "dots": 1,
            "tuplet": null,
            "tie": null
          },
          {
            "rest": false,
            "keys": [
              "c/3",
              "e/3",
              "c/4",
              "e/4"
            ],
            "duration": "16",
            "dots": 0,
            "tuplet": null,
            "tie": null
          },
          {
            "rest": false,
            "keys": [
              "c/3",
              "e/3",
              "c/4"
            ],
            "duration": "16",
            "dots": 0,
            "tuplet": null,
            "tie": null
          },
          {
            "rest": false,
            "keys": [
              "c/3",
              "c/4",
              "e/4"
            ],
            "duration": "8",
            "dots": 0,
            "tuplet": null,
            "tie": null
          }
        ]
      },
      {
        "number": 8,
        "items": [
          {
            "rest": false,
            "keys": [
              "c/3",
              "e/3",
              "c/4"
            ],
            "duration": "8",
            "dots": 0,
            "tuplet": null,
            "tie": null
          },
          {
            "rest": false,
            "keys": [
              "e/3",
              "c/4"
            ],
            "duration": "q",
            "dots": 0,
            "tuplet": null,
            "tie": null
          },
          {
            "rest": false,
            "keys": [
              "c/3",
              "e/3",
              "g/3",
              "c/4"
            ],
            "duration": "8",
            "dots": 1,
            "tuplet": null,
            "tie": null
          },
          {
            "rest": false,
            "keys": [
              "c/3",
              "e/3",
              "g/3"
            ],
            "duration": "8",
            "dots": 1,
            "tuplet": null,
            "tie": null
          },
          {
            "rest": false,
            "keys": [
              "e/3",
              "g/3"
            ],
            "duration": "16",
            "dots": 0,
            "tuplet": null,
            "tie": null
          },
          {
            "rest": false,
            "keys": [
              "e/3"
            ],
            "duration": "8",
            "dots": 0,
            "tuplet": null,
            "tie": null
          },
          {
            "rest": true,
            "keys": [],
            "duration": "16",
            "dots": 0,
            "tuplet": null,
            "tie": null
          }
        ]
      },
      {
        "number": 9,
        "items": [
          {
            "rest": true,
            "keys": [],
            "duration": "8",
            "dots": 1,
            "tuplet": null,
            "tie": null
          },
          {
            "rest": false,
            "keys": [
              "g/2"
            ],
            "duration": "16",
            "dots": 0,
            "tuplet": null,
            "tie": null
          },
          {
            "rest": false,
            "keys": [
              "g/2",
              "d/3",
              "g/3"
            ],
            "duration": "q",
            "dots": 1,
            "tuplet": null,
            "tie": null
          }
        ]
      }
    ]
  }
}